LICENSE.md
README.md
setup.cfg
setup.py
kaizen_deploy.egg-info/PKG-INFO
kaizen_deploy.egg-info/SOURCES.txt
kaizen_deploy.egg-info/dependency_links.txt
kaizen_deploy.egg-info/entry_points.txt
kaizen_deploy.egg-info/requires.txt
kaizen_deploy.egg-info/top_level.txt
src/main.py
src/templates/manifest.yaml