Metadata-Version: 2.1
Name: kaizen-deploy
Version: 1.2.4
Summary: kaizen-deploy is a Configuration Management tool used for installing Heimdall.
Author: Arjun Babu
Author-email: arbnair97@gmail.com
Maintainer: Arjun Babu
Maintainer-email: arbnair97@gmail.com
License: MIT
Keywords: kaizen-deploy
Classifier: Development Status :: 5 - Production/Stable
Requires-Python: >=3.6
License-File: LICENSE.md
